modland/MODIS_land_tile.py
modland/__init__.py
modland/constants.py
modland/dimensions.py
modland/find_modland_tiles.py
modland/get_proj4.py
modland/indices.py
modland/latlon_to_modland.py
modland/latlon_to_sinusoidal.py
modland/modland.py
modland/modland_affine.py
modland/modland_pixels.py
modland/outlines.py
modland/parsehv.py
modland/projection.py
modland/sinusoidal_to_latlon.py
modland/sinusoidal_to_modland.py
modland/transform_shape.py
modland/version.txt
modland-1.1.2.dist-info/licenses/LICENSE
modland-1.1.2.dist-info/METADATA
modland-1.1.2.dist-info/WHEEL
modland-1.1.2.dist-info/top_level.txt
modland-1.1.2.dist-info/RECORD
