Metadata-Version: 2.4
Name: modland
Version: 1.1.2
Summary: georeferencing for MODIS/VIIRS sinusoidal tiles
Author-email: "Gregory H. Halverson" <gregory.h.halverson@jpl.nasa.gov>
Project-URL: Homepage, https://github.com/JPL-Evapotranspiration-Algorithms/modland
Classifier: Programming Language :: Python :: 3
Classifier: Operating System :: OS Independent
Requires-Python: >=3.10
License-File: LICENSE
Requires-Dist: affine
Requires-Dist: geopandas
Requires-Dist: numpy
Requires-Dist: pyproj
Requires-Dist: rasterio
Requires-Dist: rasters
Requires-Dist: scipy
Requires-Dist: shapely
Provides-Extra: dev
Requires-Dist: pytest; extra == "dev"
Requires-Dist: build; extra == "dev"
Requires-Dist: twine; extra == "dev"
Dynamic: license-file
